voiceai_amp_client_sdk-2.19.2.data/data/LICENSE.txt
voiceai_amp_client_sdk-2.19.2.data/purelib/tritonclient/__init__.py
voiceai_amp_client_sdk-2.19.2.data/purelib/tritonclient/grpc/__init__.py
voiceai_amp_client_sdk-2.19.2.data/purelib/tritonclient/grpc/model_config_pb2.py
voiceai_amp_client_sdk-2.19.2.data/purelib/tritonclient/grpc/service_pb2.py
voiceai_amp_client_sdk-2.19.2.data/purelib/tritonclient/grpc/service_pb2_grpc.py
voiceai_amp_client_sdk-2.19.2.data/purelib/tritonclient/http/__init__.py
voiceai_amp_client_sdk-2.19.2.data/purelib/tritonclient/utils/__init__.py
voiceai_amp_client_sdk-2.19.2.data/purelib/tritonclientutils/__init__.py
voiceai_amp_client_sdk-2.19.2.data/purelib/tritongrpcclient/__init__.py
voiceai_amp_client_sdk-2.19.2.data/purelib/tritongrpcclient/grpc_service_pb2.py
voiceai_amp_client_sdk-2.19.2.data/purelib/tritongrpcclient/grpc_service_pb2_grpc.py
voiceai_amp_client_sdk-2.19.2.data/purelib/tritongrpcclient/model_config_pb2.py
voiceai_amp_client_sdk-2.19.2.data/purelib/tritonhttpclient/__init__.py
voiceai_amp_client_sdk-2.19.2.dist-info/LICENSE.txt
voiceai_amp_client_sdk-2.19.2.dist-info/METADATA
voiceai_amp_client_sdk-2.19.2.dist-info/WHEEL
voiceai_amp_client_sdk-2.19.2.dist-info/top_level.txt
voiceai_amp_client_sdk-2.19.2.dist-info/RECORD
